README.md
setup.py
upland_api/__init__.py
upland_api/__version__.py
upland_api/global_methods.py
upland_api.egg-info/PKG-INFO
upland_api.egg-info/SOURCES.txt
upland_api.egg-info/dependency_links.txt
upland_api.egg-info/requires.txt
upland_api.egg-info/top_level.txt
upland_api/developers/__init__.py
upland_api/developers/models/__init__.py
upland_api/developers/models/auth.py
upland_api/developers/models/buildings.py
upland_api/developers/models/cities.py
upland_api/developers/models/collections.py
upland_api/developers/models/containers.py
upland_api/developers/models/neighborhoods.py
upland_api/developers/models/properties.py
upland_api/developers/models/tracks.py
upland_api/developers/models/treasures_history.py
upland_api/developers/models/user.py
upland_api/developers/resources/__init__.py
upland_api/developers/resources/auth.py
upland_api/developers/resources/buildings.py
upland_api/developers/resources/cities.py
upland_api/developers/resources/collections.py
upland_api/developers/resources/containers.py
upland_api/developers/resources/neighborhoods.py
upland_api/developers/resources/properties.py
upland_api/developers/resources/tracks.py
upland_api/developers/resources/treasures_history.py
upland_api/developers/resources/user.py
upland_api/public/__init__.py
upland_api/public/models/__init__.py
upland_api/public/models/feature.py
upland_api/public/models/settings.py
upland_api/public/resources/__init__.py
upland_api/public/resources/feature.py
upland_api/public/resources/settings.py