Metadata-Version: 2.1
Name: upland-api
Version: 1.1.1
Summary: Python API Wrapper for Upland.me's Public and Developers API
Home-page: https://github.com/codekuu/upland-api
Author: Kevin Kuusela
Author-email: kevin@oppetinternet.se
License: UNKNOWN
Platform: UNKNOWN
Classifier: Programming Language :: Python :: 3
Classifier: Operating System :: OS Independent
Requires-Python: >=3.6
